chaosspring/__init__.py
chaosspring/actions.py
chaosspring/api.py
chaosspring/probes.py
chaostoolkit_spring-0.3.2.dist-info/LICENSE
chaostoolkit_spring-0.3.2.dist-info/METADATA
chaostoolkit_spring-0.3.2.dist-info/WHEEL
chaostoolkit_spring-0.3.2.dist-info/top_level.txt
chaostoolkit_spring-0.3.2.dist-info/RECORD
